[
    {
        "id": 1,
        "product_name": "Beatles",
        "serial_number": 1234,
        "manufacturer": "outlander",
        "category": "vinyl",
        "quantity": 2,
        "product_image": "https://dy1njwx6v16vt.cloudfront.net/wp-content/uploads/sites/44/2019/05/The-Beatles-Let-It-Be.jpg",
        "price": 24.95
    },
    {
        "id": 2,
        "product_name": "Monkees Hoodie",
        "serial_number": 12345,
        "manufacturer": "outlander",
        "category": "clothes",
        "quantity": 5,
        "product_image": "https://dy1njwx6v16vt.cloudfront.net/wp-content/uploads/sites/44/2019/05/The-Beatles-Let-It-Be.jpg",
        "price": 59.99
    },
    {
        "id": 3,
        "product_name": "Coffee Mug",
        "serial_number": 12346,
        "manufacturer": "outlander",
        "category": "merch",
        "quantity": 1,
        "product_image": "https://dy1njwx6v16vt.cloudfront.net/wp-content/uploads/sites/44/2019/05/The-Beatles-Let-It-Be.jpg",
        "price": 4.99
    },
    {
        "id": 4,
        "product_name": "Roger Waters Live",
        "serial_number": 12348,
        "manufacturer": "outlander",
        "category": "DVD/BlueRay",
        "quantity": 7,
        "product_image": "https://dy1njwx6v16vt.cloudfront.net/wp-content/uploads/sites/44/2019/05/The-Beatles-Let-It-Be.jpg",
        "price": 19.99
    },
    {
        "id": 5,
        "product_name": "Haight Ashbury Poster",
        "serial_number": 12348,
        "manufacturer": "outlander",
        "category": "Posters",
        "quantity": 1,
        "product_image": "https://dy1njwx6v16vt.cloudfront.net/wp-content/uploads/sites/44/2019/05/The-Beatles-Let-It-Be.jpg",
        "price": 9.99
    }
]


